CHANGELOG.rst
LICENSE
MANIFEST.in
README.rst
pyproject.toml
batoid_rubin/__init__.py
batoid_rubin/_version.py
batoid_rubin/align_game.py
batoid_rubin/builder.py
batoid_rubin/utils.py
batoid_rubin/visualize.py
batoid_rubin/data/download_rubin_data.py