Metadata-Version: 2.1
Name: batoid_rubin
Version: 0.5.0
Author-email: Josh Meyers <jmeyers314@gmail.com>
License-File: LICENSE
Requires-Dist: batoid
Requires-Dist: requests
